aws_eni_tagger/main.py
aws_eni_tagger/table.py
aws_eni_tagger/tags.py
aws_eni_tagger-0.1.1.dist-info/LICENSE
aws_eni_tagger-0.1.1.dist-info/METADATA
aws_eni_tagger-0.1.1.dist-info/WHEEL
aws_eni_tagger-0.1.1.dist-info/entry_points.txt
aws_eni_tagger-0.1.1.dist-info/RECORD
