Metadata-Version: 2.1
Name: aws-eni-tagger
Version: 0.1.1
Summary: Add meaningful tags to your AWS Elastic Network Interfaces
Author: EreminAnton
Author-email: mobessona2@gmail.com
Requires-Python: >=3.9,<4.0
Classifier: Programming Language :: Python :: 3
Classifier: Programming Language :: Python :: 3.9
Classifier: Programming Language :: Python :: 3.10
Classifier: Programming Language :: Python :: 3.11
Requires-Dist: aws-eni-identifier (>=0.1.3,<0.2.0)
Requires-Dist: boto3 (>=1.26.77,<2.0.0)
Requires-Dist: boto3-stubs[ec2] (>=1.26.77,<2.0.0)
Requires-Dist: hypothesis (>=6.68.2,<7.0.0)
Requires-Dist: pytest (>=7.2.1,<8.0.0)
Requires-Dist: typer (>=0.7.0,<0.8.0)
